eclipy/__init__.py
eclipy-1.0.0a2.dist-info/LICENSE.txt
eclipy-1.0.0a2.dist-info/METADATA
eclipy-1.0.0a2.dist-info/WHEEL
eclipy-1.0.0a2.dist-info/top_level.txt
eclipy-1.0.0a2.dist-info/RECORD
