Metadata-Version: 2.1
Name: eclipy
Version: 1.0.0a2
Summary: A powerful, lightweight Python library designed to provide a variety of functions.
License: MIT License
Project-URL: source, https://github.com/DevByEagle/eclipy
Project-URL: tracker, https://github.com/DevByeagle/eclipy/issues
Classifier: Development Status :: 3 - Alpha
Classifier: License :: OSI Approved :: MIT License
Classifier: Intended Audience :: Developers
Classifier: Programming Language :: Python :: 3
Classifier: Programming Language :: Python :: 3.10
Classifier: Programming Language :: Python :: 3.11
Classifier: Programming Language :: Python :: 3.12
Classifier: Programming Language :: Python :: 3.13
Classifier: Topic :: Software Development
Requires-Python: >=3.10
License-File: LICENSE.txt
